phone_iso3166/__init__.py
phone_iso3166/country.py
phone_iso3166/e164.py
phone_iso3166/e212.py
phone_iso3166/e212_names.py
phone_iso3166/errors.py
phone_iso3166/nanpa.py
phone_iso3166/network.py
phone_iso3166/py.typed
tests/__init__.py
tests/test_country.py
tests/test_map.py
tests/test_network.py
phone_iso3166-0.4.0.dist-info/LICENSE
phone_iso3166-0.4.0.dist-info/METADATA
phone_iso3166-0.4.0.dist-info/WHEEL
phone_iso3166-0.4.0.dist-info/top_level.txt
phone_iso3166-0.4.0.dist-info/RECORD
