Metadata-Version: 2.1
Name: phone-iso3166
Version: 0.4.0
Summary: Phonenumber to Country (ISO 3166-1) mapping
Home-page: UNKNOWN
Maintainer: OC dev team
Maintainer-email: devs@oc.dk
License: MIT
Keywords: phone country mobile iso3166 e164 e212 countrycode phonenumber
Platform: UNKNOWN
Classifier: License :: OSI Approved :: MIT License
Classifier: Programming Language :: Python
Classifier: Programming Language :: Python :: 2.7
Classifier: Programming Language :: Python :: 3.3
Classifier: Programming Language :: Python :: 3.4
Classifier: Programming Language :: Python :: 3.5
Classifier: Development Status :: 4 - Beta
Classifier: Intended Audience :: Developers
Classifier: Natural Language :: English
License-File: LICENSE
